haystack_integrations/components/converters/py.typed
haystack_integrations/components/converters/mistral/__init__.py
haystack_integrations/components/converters/mistral/ocr_document_converter.py
haystack_integrations/components/embedders/py.typed
haystack_integrations/components/embedders/mistral/__init__.py
haystack_integrations/components/embedders/mistral/document_embedder.py
haystack_integrations/components/embedders/mistral/text_embedder.py
haystack_integrations/components/generators/py.typed
haystack_integrations/components/generators/mistral/__init__.py
haystack_integrations/components/generators/mistral/chat/__init__.py
haystack_integrations/components/generators/mistral/chat/chat_generator.py
mistral_haystack-0.5.0.dist-info/METADATA
mistral_haystack-0.5.0.dist-info/WHEEL
mistral_haystack-0.5.0.dist-info/licenses/LICENSE.txt
mistral_haystack-0.5.0.dist-info/RECORD
